credo_runner.py
credo_runner_main.py
credo_ui/__init__.py
credo_ui/app.py
credo_ui/chat_manager.py
credo_ui/chat_storage.py
credo_ui/sidebar.py
credo_ui/streamlit_styler.py
credo_ui/ui.py
credo_ui/utils.py
credo_ui-0.0.21.dist-info/METADATA
credo_ui-0.0.21.dist-info/WHEEL
credo_ui-0.0.21.dist-info/entry_points.txt
credo_ui-0.0.21.dist-info/RECORD
